sales_pipeline/__init__.py
sales_pipeline/bronze/ingestion.py
sales_pipeline/gold/aggregation.py
sales_pipeline/pipeline/pipeline.py
sales_pipeline/silver/cleaning.py
sales_pipeline/utils/logging_config.py
sales_pipeline/utils/spark_session.py
tests/__init__.py
tests/test_gold.py
tests_ci/test_gold_ci.py
sales_pipeline-0.1.7.dist-info/METADATA
sales_pipeline-0.1.7.dist-info/WHEEL
sales_pipeline-0.1.7.dist-info/entry_points.txt
sales_pipeline-0.1.7.dist-info/top_level.txt
sales_pipeline-0.1.7.dist-info/RECORD
