Metadata-Version: 2.4
Name: sales-pipeline
Version: 0.1.7
Summary: Pipeline de traitement Spark Bronze / Silver / Gold
Author: Hugo Boulenger
Requires-Python: >=3.8
Requires-Dist: pyspark
Requires-Dist: pyyaml
Provides-Extra: dev
Requires-Dist: pytest; extra == "dev"
Requires-Dist: build; extra == "dev"
Requires-Dist: wheel; extra == "dev"
